{
  "template": "https://github.com/sierra-moxon/cookiecutter-pypackage",
  "commit": "f5d18a3c2ee59eab53ddab5dc1e9ce909f3ed83c",
  "checkout": null,
  "context": {
    "cookiecutter": {
      "full_name": "Sierra Moxon",
      "email": "sierra.taylor@gmail.com",
      "github_username": "sierra-moxon",
      "project_name": "test_cruft_fork",
      "project_slug": "test_cruft_fork",
      "project_short_description": "tester using forked template",
      "pypi_username": "smoxon",
      "version": "0.0.1",
      "use_pytest": "y",
      "add_pyup_badge": "y",
      "command_line_interface": "Click",
      "create_author_file": "y",
      "open_source_license": "MIT license",
      "_template": "https://github.com/sierra-moxon/cookiecutter-pypackage"
    }
  },
  "directory": null
}
